frag/__init__.py
frag/alysis/__init__.py
frag/alysis/cluster.py
frag/alysis/improve.py
frag/alysis/models.py
frag/alysis/run_clustering.py
frag/conf/__init__.py
frag/conf/functions.py
frag/network/__init__.py
frag/network/decorate.py
frag/network/django_models.py
frag/network/get_from_fragalysis.py
frag/network/grow.py
frag/network/models.py
frag/network/query.py
frag/network/substruct.py
frag/network/scripts/__init__.py
frag/network/scripts/analyse_lib.py
frag/network/scripts/annotate_nodes.py
frag/network/scripts/batch_convert.py
frag/network/scripts/build_db.py
frag/network/scripts/colate_all.py
frag/network/scripts/collect.py
frag/network/scripts/decorate_smi.py
frag/network/scripts/header_shred.py
frag/network/scripts/parallel_build_db.py
frag/network/scripts/query_db.py
frag/network/scripts/split_input.py
frag/network/scripts/upload_db.py
frag/network/scripts/write_results.py
frag/tests/__init__.py
frag/tests/test_cluster.py
frag/tests/test_network.py
frag/tests/test_parser.py
frag/tests/test_rdkit.py
frag/tests/test_vector.py
frag/utils/__init__.py
frag/utils/network_utils.py
frag/utils/parser.py
frag/utils/rdkit_utils.py
frag/utils/vector_utils.py
frag/utils/writer.py
frag/utils/data/RDKitPh4.fdef
frag/vector/__init__.py
frag/vector/exit_vector.py
im_fragalysis-1.2.5.dist-info/LICENSE
im_fragalysis-1.2.5.dist-info/METADATA
im_fragalysis-1.2.5.dist-info/WHEEL
im_fragalysis-1.2.5.dist-info/entry_points.txt
im_fragalysis-1.2.5.dist-info/top_level.txt
im_fragalysis-1.2.5.dist-info/RECORD
