Metadata-Version: 2.1
Name: im-fragalysis
Version: 1.2.5
Summary: Library for fragment based analysis
Home-page: https://github.com/xchem/fragalysis.git
Author: Rachael Skyner
Author-email: rachael.skyner@diamond.ac.uk
License: Apache 2.0
Platform: UNKNOWN
Classifier: Development Status :: 3 - Alpha
Classifier: Intended Audience :: Developers
Classifier: Topic :: Software Development :: Build Tools
Classifier: License :: OSI Approved :: Apache Software License
Classifier: Programming Language :: Python :: 2
Classifier: Programming Language :: Python :: 2.6
Classifier: Programming Language :: Python :: 2.7
Classifier: Programming Language :: Python :: 3
Classifier: Programming Language :: Python :: 3.2
Classifier: Programming Language :: Python :: 3.3
Classifier: Programming Language :: Python :: 3.4
Classifier: Programming Language :: Python :: 3.5
License-File: LICENSE
Requires-Dist: ipython (>=5.4.1)
Requires-Dist: tqdm (==4.48.2)
Requires-Dist: neo4j-driver (==4.4.2)
Requires-Dist: numpy (>=1.16.6)
Requires-Dist: nose (>=1.3.7)
Requires-Dist: coveralls (>=1.11.1)
Requires-Dist: requests (>=2.24.0)
Provides-Extra: dev
Requires-Dist: check-manifest ; extra == 'dev'
Provides-Extra: test
Requires-Dist: coverage ; extra == 'test'
